Flask_RESTive_MongoDB-0.0.1.dist-info/DESCRIPTION.rst
Flask_RESTive_MongoDB-0.0.1.dist-info/METADATA
Flask_RESTive_MongoDB-0.0.1.dist-info/RECORD
Flask_RESTive_MongoDB-0.0.1.dist-info/WHEEL
Flask_RESTive_MongoDB-0.0.1.dist-info/metadata.json
Flask_RESTive_MongoDB-0.0.1.dist-info/top_level.txt
flask_restive_mongodb/__init__.py
flask_restive_mongodb/models.py
flask_restive_mongodb/services.py
flask_restive_mongodb/utils.py
