Metadata-Version: 2.0
Name: Flask-RESTive-MongoDB
Version: 0.0.1
Summary: Flask-RESTive extension to work with MongoDB.
Home-page: https://github.com/left-join/flask-restive-mongodb
Author: left-join
Author-email: left-join@riseup.net
License: MIT
Download-URL: https://github.com/left-join/flask-restive-mongodb.git
Keywords: Flask-RESTive,MongoDB
Platform: any
Classifier: Environment :: Web Environment
Classifier: Intended Audience :: Developers
Classifier: License :: OSI Approved :: MIT License
Classifier: Operating System :: OS Independent
Classifier: Programming Language :: Python
Classifier: Topic :: Internet :: WWW/HTTP :: Dynamic Content
Classifier: Topic :: Software Development :: Libraries :: Python Modules
Requires-Dist: flask-restive (>=0.0.3)
Requires-Dist: pymongo (>=3.5.1)
Requires-Dist: mongoengine (>=0.13.0)
